dwave_micro_client_dimod/__init__.py
dwave_micro_client_dimod/composite.py
dwave_micro_client_dimod/package_info.py
dwave_micro_client_dimod/response.py
dwave_micro_client_dimod/sampler.py
dwave_micro_client_dimod/tiling.py
dwave_micro_client_dimod-0.3.1.dist-info/DESCRIPTION.rst
dwave_micro_client_dimod-0.3.1.dist-info/METADATA
dwave_micro_client_dimod-0.3.1.dist-info/RECORD
dwave_micro_client_dimod-0.3.1.dist-info/WHEEL
dwave_micro_client_dimod-0.3.1.dist-info/metadata.json
dwave_micro_client_dimod-0.3.1.dist-info/top_level.txt
