Metadata-Version: 1.0
Name: dwave_micro_client_dimod
Version: 0.3.1
Summary: dimod wrapper for the D-Wave Micro Client
Home-page: https://github.com/dwavesystems/dwave_micro_client_dimod
Author: D-Wave Systems Inc.
Author-email: acondello@dwavesys.com
License: Apache 2.0
Platform: UNKNOWN
